.coveragerc
.gitignore
.travis.yml
LICENSE.mkd
README.mkd
pytest.ini
setup.cfg
setup.py
tox.ini
virt-backup
.github/PULL_REQUEST_TEMPLATE.md
docs/.gitignore
docs/Makefile
docs/backup.rst
docs/clean.rst
docs/conf.py
docs/config.rst
docs/data_map.rst
docs/index.rst
docs/make.bat
docs/quickstart.rst
docs/_static/theme_override.css
example/config.yml
example/virt-backup-clean.service
tests/conftest.py
tests/test_compat_layers_config.py
tests/test_compat_layers_definition.py
tests/test_compat_layers_pending_info.py
tests/test_complete_backup.py
tests/test_complete_group.py
tests/test_config.py
tests/test_domain.py
tests/test_group.py
tests/test_main.py
tests/test_packagers.py
tests/test_pending_backup.py
tests/test_snapshot.py
tests/test_unsupported.py
tests/helper/__init__.py
tests/helper/datetime.py
tests/helper/testdomain.xml
tests/helper/virt_backup.py
tests/testconfig/config.yml
tests/testconfig/versions/0.4/post.yml
tests/testconfig/versions/0.4/pre.yml
tests/testconfig/versions/full/0.1.yml
tests/testconfig/versions/full/0.4.yml
virt_backup/__init__.py
virt_backup/__main__.py
virt_backup/config.py
virt_backup/domains.py
virt_backup/exceptions.py
virt_backup/tools.py
virt_backup.egg-info/PKG-INFO
virt_backup.egg-info/SOURCES.txt
virt_backup.egg-info/dependency_links.txt
virt_backup.egg-info/entry_points.txt
virt_backup.egg-info/requires.txt
virt_backup.egg-info/top_level.txt
virt_backup/backups/__init__.py
virt_backup/backups/complete.py
virt_backup/backups/pending.py
virt_backup/backups/snapshot.py
virt_backup/backups/packagers/__init__.py
virt_backup/backups/packagers/directory.py
virt_backup/backups/packagers/tar.py
virt_backup/backups/packagers/unsupported.py
virt_backup/backups/packagers/zstd.py
virt_backup/compat_layers/__init__.py
virt_backup/compat_layers/config.py
virt_backup/compat_layers/definition.py
virt_backup/compat_layers/pending_info.py
virt_backup/groups/__init__.py
virt_backup/groups/complete.py
virt_backup/groups/pattern.py
virt_backup/groups/pending.py