Metadata-Version: 2.1
Name: virt-backup
Version: 0.5.5
Summary: Automatic backups for libvirt
Home-page: https://github.com/Anthony25/virt-backup
Author: Anthony25 <Anthony Ruhier>
Author-email: anthony.ruhier@gmail.com
License: Simplified BSD
Keywords: libvirt
Classifier: Operating System :: POSIX :: Linux
Classifier: Programming Language :: Python :: 3 :: Only
Classifier: License :: OSI Approved :: BSD License
Provides-Extra: zstd
License-File: LICENSE.mkd
